mci/__init__.py
mci/mci.py
mci/py.typed
mci/assets/example_toolset.mci.json
mci/assets/example_toolset.mci.yaml
mci/assets/gitignore
mci/assets/mci.json
mci/assets/mci.yaml
mci/cli/__init__.py
mci/cli/add.py
mci/cli/envs.py
mci/cli/install.py
mci/cli/list.py
mci/cli/run.py
mci/cli/validate.py
mci/cli/formatters/__init__.py
mci/cli/formatters/env_formatter.py
mci/cli/formatters/json_formatter.py
mci/cli/formatters/table_formatter.py
mci/cli/formatters/yaml_formatter.py
mci/core/__init__.py
mci/core/config.py
mci/core/dynamic_server.py
mci/core/file_finder.py
mci/core/mci_client.py
mci/core/mcp_server.py
mci/core/schema_editor.py
mci/core/tool_converter.py
mci/core/tool_manager.py
mci/core/validator.py
mci/utils/__init__.py
mci/utils/dotenv.py
mci/utils/env_scanner.py
mci/utils/error_formatter.py
mci/utils/error_handler.py
mci/utils/timestamp.py
mci/utils/validation.py
mcix-1.1.0.dist-info/METADATA
mcix-1.1.0.dist-info/WHEEL
mcix-1.1.0.dist-info/entry_points.txt
mcix-1.1.0.dist-info/licenses/LICENSE
mcix-1.1.0.dist-info/RECORD
