Metadata-Version: 2.4
Name: mcix
Version: 1.1.0
Summary: CLI tool designed to manage MCI (Model Context Interface) schemas and dynamically run MCP servers using defined MCI toolsets 
Project-URL: Repository, https://github.com/Model-Context-Interface/mci
Project-URL: Homepage, https://github.com/Model-Context-Interface
Project-URL: Documentation, https://usemci.dev/
Author-email: maestroerror <revaz@usemci.dev>
License-Expression: MIT
License-File: LICENSE
Classifier: Development Status :: 4 - Beta
Classifier: Intended Audience :: Developers
Classifier: Operating System :: OS Independent
Classifier: Programming Language :: Python
Classifier: Programming Language :: Python :: 3
Classifier: Programming Language :: Python :: 3.11
Classifier: Programming Language :: Python :: 3.12
Classifier: Programming Language :: Python :: 3.13
Classifier: Typing :: Typed
Requires-Python: <4.0,>=3.11
Requires-Dist: click>=8.3.0
Requires-Dist: mci-py>=1.2
Requires-Dist: mcp>=1.19.0
Requires-Dist: pytest-cov>=7.0.0
Requires-Dist: python-dotenv>=1.2.1
Requires-Dist: pyyaml>=6.0.3
Requires-Dist: rich>=14.2.0
